pulumi_webflow/__init__.py
pulumi_webflow/_inputs.py
pulumi_webflow/_utilities.py
pulumi_webflow/asset.py
pulumi_webflow/asset_folder.py
pulumi_webflow/collection.py
pulumi_webflow/collection_field.py
pulumi_webflow/collection_item.py
pulumi_webflow/ecommerce_settings.py
pulumi_webflow/get_authorized_user.py
pulumi_webflow/get_token_info.py
pulumi_webflow/outputs.py
pulumi_webflow/page_content.py
pulumi_webflow/page_custom_code.py
pulumi_webflow/page_data.py
pulumi_webflow/provider.py
pulumi_webflow/pulumi-plugin.json
pulumi_webflow/py.typed
pulumi_webflow/redirect.py
pulumi_webflow/registered_script.py
pulumi_webflow/robots_txt.py
pulumi_webflow/site.py
pulumi_webflow/site_custom_code.py
pulumi_webflow/user.py
pulumi_webflow/webhook.py
pulumi_webflow/config/__init__.py
pulumi_webflow/config/__init__.pyi
pulumi_webflow/config/vars.py
pulumi_webflow-0.9.1.dist-info/METADATA
pulumi_webflow-0.9.1.dist-info/WHEEL
pulumi_webflow-0.9.1.dist-info/top_level.txt
pulumi_webflow-0.9.1.dist-info/RECORD
