Metadata-Version: 2.4
Name: pulumi_webflow
Version: 0.9.1
Summary: Unofficial community-maintained Pulumi provider for managing Webflow sites, redirects, and robots.txt. Not affiliated with Pulumi Corporation or Webflow, Inc.
Home-page: https://github.com/JDetmar/pulumi-webflow
Project-URL: Repository, https://github.com/JDetmar/pulumi-webflow
Requires-Python: >=3.9
Requires-Dist: parver>=0.2.1
Requires-Dist: pulumi<4.0.0,>=3.165.0
Requires-Dist: semver>=2.8.1
Requires-Dist: typing-extensions<5,>=4.11; python_version < "3.11"
Dynamic: description
Dynamic: description-content-type
Dynamic: home-page
Dynamic: project-url
Dynamic: requires-dist
Dynamic: requires-python
Dynamic: summary
